love_tell_ai_mcp_v2/__init__.py
love_tell_ai_mcp_v2-0.1.1.dist-info/WHEEL
love_tell_ai_mcp_v2-0.1.1.dist-info/entry_points.txt
love_tell_ai_mcp_v2-0.1.1.dist-info/METADATA
love_tell_ai_mcp_v2-0.1.1.dist-info/RECORD
