Metadata-Version: 2.3
Name: love-tell-ai-mcp-v2
Version: 0.1.1
Summary: love-tell-ai-mcp v2
Author: splendor023
Author-email: splendor023 <splendor023@gmail.com>
Requires-Dist: dashscope>=1.24.2
Requires-Dist: fastmcp>=2.11.3
Requires-Python: >=3.12
